niftymic_gui/__init__.py
niftymic_gui/exceptions.py
niftymic_gui/gui.py
niftymic_gui/helpers.py
niftymic_gui/main.py
niftymic_gui/mri_process.py
niftymic_gui/process_utils.py
niftymic_gui/reconstruction.py
niftymic_gui/settings.py
niftymic_gui-0.0.1.dist-info/entry_points.txt
niftymic_gui-0.0.1.dist-info/WHEEL
niftymic_gui-0.0.1.dist-info/METADATA
niftymic_gui-0.0.1.dist-info/RECORD
